creditscoring/__init__.py
creditscoring/binning/__init__.py
creditscoring/scorecard/__init__.py
creditscoring/utils/__init__.py
credit_scoring_toolkit-0.0.2.dist-info/LICENSE
credit_scoring_toolkit-0.0.2.dist-info/METADATA
credit_scoring_toolkit-0.0.2.dist-info/WHEEL
credit_scoring_toolkit-0.0.2.dist-info/top_level.txt
credit_scoring_toolkit-0.0.2.dist-info/RECORD
