Metadata-Version: 2.1
Name: credit-scoring-toolkit
Version: 0.0.2
Summary: A Python package designed as a credit scoring toolkit.
Home-page: https://github.com/Keris/creditscoring
Author: Liqiang Du
Author-email: dlq137@gmail.com
License: MIT
Keywords: finance,credit,scorecard,regression,machine learning
Platform: UNKNOWN
Classifier: Development Status :: 1 - Planning
Classifier: Intended Audience :: Developers
Classifier: Intended Audience :: Financial and Insurance Industry
Classifier: Intended Audience :: Science/Research
Classifier: Programming Language :: Python :: 3.6
Classifier: Programming Language :: Python :: 3.7
Classifier: License :: OSI Approved :: MIT License
Classifier: Topic :: Office/Business :: Financial
Classifier: Topic :: Software Development
Classifier: Topic :: Software Development :: Libraries
Classifier: Topic :: Software Development :: Libraries :: Python Modules
Requires-Python: >=3.6
Requires-Dist: matplotlib (>=1.1)
Requires-Dist: numpy (>=0.7.0)
Requires-Dist: pandas (>=0.20.1)
Requires-Dist: scipy (>=0.10.0)
Requires-Dist: seaborn (>=0.8.0)
Requires-Dist: scikit-learn (>=0.18)
